{"actions": 15183, "added_lines": 669302.0, "added_lines_30": 4835.0, "added_lines_365": 39436.0, "added_lines_7": 3326.0, "authors": 1, "authors_30": 1, "authors_365": 1, "authors_7": 1, "avg_commits_author": 3015.0, "avg_commits_month": 51.98, "avg_files_author": 6525.0, "avg_files_month": 112.5, "branches": 14, "commits": 3015, "commits_30": 92, "commits_365": 668, "commits_7": 68, "committers": 107, "diff_netadded_lines_30": 3953.0, "diff_netadded_lines_365": -176814.0, "diff_netadded_lines_7": 2224.0, "diff_netauthors_30": 0, "diff_netauthors_365": 0, "diff_netauthors_7": 0, "diff_netcommits_30": 70, "diff_netcommits_365": -411, "diff_netcommits_7": 59, "diff_netfiles_30": 181, "diff_netfiles_365": -1767, "diff_netfiles_7": 78, "diff_netnewauthors_30": 0, "diff_netnewauthors_365": 0, "diff_netnewauthors_7": 0, "diff_netremoved_lines_30": 3591.0, "diff_netremoved_lines_365": -135791.0, "diff_netremoved_lines_7": 3122.0, "files": 6525, "files_30": 262, "files_365": 1305, "files_7": 109, "first_date": "2011-05-28", "last_date": "2016-04-03", "newauthors": 1, "newauthors_30": 0, "newauthors_365": 0, "newauthors_7": 0, "percentage_added_lines_30": 448, "percentage_added_lines_365": 81, "percentage_added_lines_7": 201, "percentage_authors_30": 0, "percentage_authors_365": 0, "percentage_authors_7": 0, "percentage_commits_30": 318, "percentage_commits_365": 38, "percentage_commits_7": 655, "percentage_files_30": 223, "percentage_files_365": 57, "percentage_files_7": 251, "percentage_newauthors_30": 0, "percentage_newauthors_365": 0, "percentage_newauthors_7": 0, "percentage_removed_lines_30": 799, "percentage_removed_lines_365": 79, "percentage_removed_lines_7": 1160, "removed_lines": 373240.0, "removed_lines_30": 4040.0, "removed_lines_365": 34227.0, "removed_lines_7": 3391.0, "repositories": 44}