{"abandoned": 1349, "abandoned_30": 61, "abandoned_365": 578, "abandoned_7": 1, "bmiscr_30": 0, "bmiscr_365": 0, "bmiscr_7": 0, "closed": 1902, "closers": 359, "closers_30": 52, "closers_365": 231, "closers_7": 5, "diff_netabandoned_30": 16, "diff_netabandoned_365": 554, "diff_netabandoned_7": -12, "diff_netbmiscr_30": 0, "diff_netbmiscr_365": 0, "diff_netbmiscr_7": 0, "diff_netclosers_30": 10, "diff_netclosers_365": 211, "diff_netclosers_7": -14, "diff_netmerged_30": 10, "diff_netmerged_365": 448, "diff_netmerged_7": -4, "diff_netmergers_30": 0, "diff_netmergers_365": 6, "diff_netmergers_7": 0, "diff_netparticipants_30": 6, "diff_netparticipants_365": 268, "diff_netparticipants_7": -13, "diff_netsubmitted_30": 18, "diff_netsubmitted_365": 979, "diff_netsubmitted_7": -8, "diff_netsubmitters_30": -3, "diff_netsubmitters_365": 116, "diff_netsubmitters_7": -11, "first_date": "2011-10-04", "last_date": "2016-02-12", "merged": 553, "merged_30": 45, "merged_365": 460, "merged_7": 4, "mergers": 14, "mergers_30": 5, "mergers_365": 7, "mergers_7": 2, "participants": 661, "participants_30": 99, "participants_365": 457, "participants_7": 35, "pending": 307, "percentage_abandoned_30": 35, "percentage_abandoned_365": 2308, "percentage_abandoned_7": 92, "percentage_bmiscr_30": 0, "percentage_bmiscr_365": 0, "percentage_bmiscr_7": 0, "percentage_closers_30": 23, "percentage_closers_365": 1055, "percentage_closers_7": 73, "percentage_merged_30": 28, "percentage_merged_365": 3733, "percentage_merged_7": 50, "percentage_mergers_30": 0, "percentage_mergers_365": 600, "percentage_mergers_7": 0, "percentage_participants_30": 6, "percentage_participants_365": 141, "percentage_participants_7": 27, "percentage_submitted_30": 16, "percentage_submitted_365": 517, "percentage_submitted_7": 25, "percentage_submitters_30": 6, "percentage_submitters_365": 103, "percentage_submitters_7": 57, "repositories": 1, "submitted": 2209, "submitted_30": 125, "submitted_365": 1168, "submitted_7": 24, "submitters": 422, "submitters_30": 41, "submitters_365": 228, "submitters_7": 8, "timeto_close_avg": 56.95, "timeto_close_median": 4.41, "timeto_merge_avg": 16.17, "timeto_merge_median": 0.85}