{"allhistory_participants": 1351, "bmitickets": 85.69, "bmitickets_30": 79, "bmitickets_365": 78, "bmitickets_7": 110, "changed": 4969, "changed_30": 296, "changed_365": 2448, "changed_7": 140, "changers": 865, "changers_30": 92, "changers_365": 566, "changers_7": 50, "closed": 4372, "closed_30": 149, "closed_365": 1567, "closed_7": 65, "closers": 236, "closers_30": 24, "closers_365": 102, "closers_7": 11, "diff_netbmitickets_30": 22, "diff_netbmitickets_365": 3, "diff_netbmitickets_7": 69, "diff_netchanged_30": -42, "diff_netchanged_365": 1368, "diff_netchanged_7": 73, "diff_netchangers_30": -59, "diff_netchangers_365": 303, "diff_netchangers_7": 11, "diff_netclosed_30": 6, "diff_netclosed_365": 799, "diff_netclosed_7": 46, "diff_netclosers_30": -13, "diff_netclosers_365": 57, "diff_netclosers_7": 2, "diff_netopened_30": -61, "diff_netopened_365": 976, "diff_netopened_7": 13, "diff_netopeners_30": -20, "diff_netopeners_365": 296, "diff_netopeners_7": 5, "domains": 134, "first_date": "2011-10-04", "last_date": "2016-01-22", "opened": 5102, "opened_30": 187, "opened_365": 1991, "opened_7": 59, "openers": 808, "openers_30": 97, "openers_365": 485, "openers_7": 38, "organizations": 0, "percentage_bmitickets_30": 38, "percentage_bmitickets_365": 4, "percentage_bmitickets_7": 168, "percentage_changed_30": 12, "percentage_changed_365": 126, "percentage_changed_7": 108, "percentage_changers_30": 39, "percentage_changers_365": 115, "percentage_changers_7": 28, "percentage_closed_30": 4, "percentage_closed_365": 104, "percentage_closed_7": 242, "percentage_closers_30": 35, "percentage_closers_365": 126, "percentage_closers_7": 22, "percentage_opened_30": 24, "percentage_opened_365": 96, "percentage_opened_7": 28, "percentage_openers_30": 17, "percentage_openers_365": 156, "percentage_openers_7": 15, "trackers": 45, "type": "github", "url": "https://api.github.com/repos/joomla/joomla-cms/issues"}