{"allhistory_participants": 1671, "bmitickets": 84.93, "bmitickets_30": 88, "bmitickets_365": 82, "bmitickets_7": 119, "changed": 5915, "changed_30": 623, "changed_365": 3282, "changed_7": 188, "changers": 1040, "changers_30": 200, "changers_365": 709, "changers_7": 65, "closed": 5074, "closed_30": 380, "closed_365": 2072, "closed_7": 112, "closers": 279, "closers_30": 51, "closers_365": 147, "closers_7": 18, "diff_netbmitickets_30": 11, "diff_netbmitickets_365": 18, "diff_netbmitickets_7": 37, "diff_netchanged_30": 282, "diff_netchanged_365": 1961, "diff_netchanged_7": 25, "diff_netchangers_30": 69, "diff_netchangers_365": 395, "diff_netchangers_7": -19, "diff_netclosed_30": 185, "diff_netclosed_365": 1381, "diff_netclosed_7": 25, "diff_netclosers_30": 29, "diff_netclosers_365": 107, "diff_netclosers_7": 0, "diff_netopened_30": 176, "diff_netopened_365": 1439, "diff_netopened_7": -11, "diff_netopeners_30": 91, "diff_netopeners_365": 441, "diff_netopeners_7": -9, "domains": 154, "first_date": "2011-10-04", "last_date": "2016-04-07", "opened": 5974, "opened_30": 428, "opened_365": 2509, "opened_7": 94, "openers": 1038, "openers_30": 206, "openers_365": 685, "openers_7": 57, "organizations": 0, "percentage_bmitickets_30": 14, "percentage_bmitickets_365": 28, "percentage_bmitickets_7": 45, "percentage_changed_30": 82, "percentage_changed_365": 148, "percentage_changed_7": 15, "percentage_changers_30": 52, "percentage_changers_365": 125, "percentage_changers_7": 22, "percentage_closed_30": 94, "percentage_closed_365": 199, "percentage_closed_7": 28, "percentage_closers_30": 131, "percentage_closers_365": 267, "percentage_closers_7": 0, "percentage_opened_30": 69, "percentage_opened_365": 134, "percentage_opened_7": 10, "percentage_openers_30": 79, "percentage_openers_365": 180, "percentage_openers_7": 13, "trackers": 45, "type": "github", "url": "https://api.github.com/repos/joomla/joomla-cms/issues"}