{"actions": 238027, "added_lines": 6645451.0, "added_lines_30": 6342.0, "added_lines_365": 131340.0, "added_lines_7": 1684.0, "authors": 608, "authors_30": 36, "authors_365": 185, "authors_7": 11, "avg_commits_author": 45.8, "avg_commits_month": 222.02, "avg_files_author": 46.55, "avg_files_month": 225.66, "branches": 8, "commits": 27753, "commits_30": 208, "commits_365": 2359, "commits_7": 47, "committers": 608, "diff_netadded_lines_30": -204.0, "diff_netadded_lines_365": -367269.0, "diff_netadded_lines_7": -136.0, "diff_netauthors_30": 5, "diff_netauthors_365": -44, "diff_netauthors_7": -6, "diff_netcommits_30": 94, "diff_netcommits_365": -292, "diff_netcommits_7": -10, "diff_netfiles_30": -3234, "diff_netfiles_365": -1600, "diff_netfiles_7": -37, "diff_netnewauthors_30": 3, "diff_netnewauthors_365": -51, "diff_netnewauthors_7": 1, "diff_netremoved_lines_30": -399.0, "diff_netremoved_lines_365": -267679.0, "diff_netremoved_lines_7": 819.0, "files": 28208, "files_30": 393, "files_365": 5784, "files_7": 93, "first_date": "2005-09-15", "last_date": "2016-02-24", "newauthors": 608, "newauthors_30": 7, "newauthors_365": 89, "newauthors_7": 2, "percentage_added_lines_30": 3, "percentage_added_lines_365": 73, "percentage_added_lines_7": 7, "percentage_authors_30": 16, "percentage_authors_365": 19, "percentage_authors_7": 35, "percentage_commits_30": 82, "percentage_commits_365": 11, "percentage_commits_7": 17, "percentage_files_30": 89, "percentage_files_365": 21, "percentage_files_7": 28, "percentage_newauthors_30": 75, "percentage_newauthors_365": 36, "percentage_newauthors_7": 100, "percentage_removed_lines_30": 7, "percentage_removed_lines_365": 74, "percentage_removed_lines_7": 71, "removed_lines": 5222777.0, "removed_lines_30": 4839.0, "removed_lines_365": 93838.0, "removed_lines_7": 1962.0, "repositories": 1}